<system>
	<name>HD 212301</name>
	<rightascension>22 27 30</rightascension>
	<declination>-77 43 04</declination>
	<distance errorminus="2.11" errorplus="1.95">52.72</distance>
	<star>
		<name>HD 212301</name>
		<mass errorminus="0.06" errorplus="0.06">1.05</mass>
		<magV errorminus="0.011" errorplus="0.011">7.77</magV>
		<magB errorminus="0.016" errorplus="0.016">8.314</magB>
		<magJ errorminus="0.020" errorplus="0.020">6.765</magJ>
		<magH errorminus="0.029" errorplus="0.029">6.522</magH>
		<magK errorminus="0.021" errorplus="0.021">6.466</magK>
		<temperature errorminus="28.00" errorplus="28.00">5998.0</temperature>
		<age errorminus="2.4" errorplus="2.4">5.9</age>
		<metallicity errorminus="0.040" errorplus="0.040">0.18</metallicity>
		<spectraltype>F8 V</spectraltype>
		<planet>
			<name>HD 212301 b</name>
			<mass type="Radial Velocity">0.4</mass>
			<radius>1.07</radius>
			<period errorminus="2.8e-05" errorplus="2.8e-05">2.245715</period>
			<semimajoraxis>0.036</semimajoraxis>
			<eccentricity errorminus="0.0147" errorplus="0.0365">0.0147</eccentricity>
			<periastron errorminus="85.6" errorplus="85.6">172.8</periastron>
			<periastrontime>2453388.9</periastrontime>
			<maximumrvtime>2453388.9</maximumrvtime>
			<discoverymethod>RV</discoverymethod>
			<lastupdate>16/11/29</lastupdate>
			<discoveryyear>2005</discoveryyear>
		</planet>
	</star>
</system>
