<system>
	<name>HD 330075</name>
	<rightascension>15 49 37</rightascension>
	<declination>-49 57 47</declination>
	<distance errorminus="4.06" errorplus="3.49">50.20</distance>
	<star>
		<name>HD 330075</name>
		<mass errorminus="0.10" errorplus="0.10">0.95</mass>
		<magV errorminus="0.023" errorplus="0.023">9.36</magV>
		<magB errorminus="0.036" errorplus="0.036">10.232</magB>
		<magJ errorminus="0.025" errorplus="0.025">7.725</magJ>
		<magH errorminus="0.027" errorplus="0.027">7.253</magH>
		<magK errorminus="0.020" errorplus="0.020">7.171</magK>
		<temperature errorminus="53.00" errorplus="53.00">6295.0</temperature>
		<age>6.21</age>
		<metallicity errorminus="0.060" errorplus="0.060">0.03</metallicity>
		<spectraltype>G5</spectraltype>
		<planet>
			<name>HD 330075 b</name>
			<mass type="Radial Velocity">0.62</mass>
			<radius>1.06</radius>
			<period errorminus="0.00187" errorplus="0.00187">3.6413</period>
			<semimajoraxis>0.039</semimajoraxis>
			<eccentricity errorminus="0.0684" errorplus="0.0187">0.0187</eccentricity>
			<periastron errorminus="91.2" errorplus="91.2">38.2</periastron>
			<periastrontime errorminus="0.003000" errorplus="0.003000">2452968.399</periastrontime>
			<maximumrvtime errorminus="0.003000" errorplus="0.003000">2452968.399</maximumrvtime>
			<temperature>990</temperature>
			<discoverymethod>RV</discoverymethod>
			<lastupdate>16/11/29</lastupdate>
			<discoveryyear>2004</discoveryyear>
		</planet>
	</star>
</system>
