<system>
	<name>Kepler-1205</name>
	<rightascension>19 21 07</rightascension>
	<declination>+41 30 54</declination>
	<distance errorminus="48.14" errorplus="50.16">766.00</distance>
	<star>
		<name>Kepler-1205</name>
		<mass errorminus="0.05" errorplus="0.04">0.84</mass>
		<radius errorminus="0.05" errorplus="0.05">0.81</radius>
		<magV>15.143</magV>
		<magJ errorminus="0.026" errorplus="0.026">13.87</magJ>
		<magH errorminus="0.028" errorplus="0.028">13.409</magH>
		<magK errorminus="0.037" errorplus="0.037">13.262</magK>
		<temperature errorminus="71.27" errorplus="84.83">5226.0</temperature>
		<age errorminus="3.010" errorplus="6.140">4.900</age>
		<metallicity errorminus="0.165" errorplus="0.162">-0.04</metallicity>
		<planet>
			<name>Kepler-1205 b</name>
			<radius errorminus="0.008" errorplus="0.009">0.126</radius>
			<period errorminus="1.6e-06" errorplus="1.6e-06">1.07839035</period>
			<discoverymethod>transit</discoverymethod>
			<transittime errorminus=".001250" errorplus="0.001250" unit="JD">2454966.249750</transittime>
			<lastupdate>16/11/29</lastupdate>
			<discoveryyear>2016</discoveryyear>
		</planet>
	</star>
</system>
