<system>
	<name>Kepler-1261</name>
	<rightascension>19 00 56</rightascension>
	<declination>+48 48 24</declination>
	<star>
		<name>Kepler-1261</name>
		<mass errorminus="0.04" errorplus="0.03">0.82</mass>
		<radius errorminus="0.03" errorplus="0.03">0.77</radius>
		<temperature errorminus="44.5" errorplus="48.3">5006.0</temperature>
		<metallicity errorminus="0.16" errorplus="0.15">0.03</metallicity>
		<planet>
			<name>Kepler-1261 b</name>
			<list>Confirmed planets</list>
			<radius errorminus="0.012" errorplus="0.012">0.202</radius>
			<period errorminus="0.000314400" errorplus="0.000314400">48.430899100</period>
			<description>This planet was discovered by the NASA Kepler spacecraft and is part of the May 10th 2016 data release. Although not many details are known about this particular system yet, it has a very low probability of being a false positive.</description>
			<discoverymethod>transit</discoverymethod>
			<istransiting>1</istransiting>
			<new>1</new>
			<lastupdate>16/05/10</lastupdate>
			<discoveryyear>2016</discoveryyear>
		</planet>
	</star>
</system>
