<system>
	<name>Kepler-966</name>
	<rightascension>19 49 04</rightascension>
	<declination>+50 07 18</declination>
	<distance errorminus="85.79" errorplus="197.77">773.00</distance>
	<star>
		<name>Kepler-966</name>
		<mass errorminus="0.07" errorplus="0.07">1.02</mass>
		<radius errorminus="0.1" errorplus="0.26">1.02</radius>
		<magV>14.422</magV>
		<magJ errorminus="0.025" errorplus="0.025">13.12</magJ>
		<magH errorminus="0.019" errorplus="0.019">12.749</magH>
		<magK errorminus="0.025" errorplus="0.025">12.745</magK>
		<temperature errorminus="184.03" errorplus="113.67">5840.0</temperature>
		<age errorminus="2.310" errorplus="2.800">4.070</age>
		<metallicity errorminus="0.157" errorplus="0.132">0.04</metallicity>
		<planet>
			<name>Kepler-966 b</name>
			<radius errorminus="0.052" errorplus="0.104">0.368</radius>
			<period errorminus="0.0004523" errorplus="0.0004523">99.747622</period>
			<discoverymethod>transit</discoverymethod>
			<transittime errorminus=".002920" errorplus="0.002920" unit="JD">2455041.395370</transittime>
			<lastupdate>16/11/29</lastupdate>
			<discoveryyear>2016</discoveryyear>
		</planet>
	</star>
</system>
