<system>
	<name>Kepler-255</name>
	<rightascension>19 44 15</rightascension>
	<declination>+45 58 36</declination>
	<star>
		<name>Kepler-255</name>
		<mass>0.97</mass>
		<radius errorminus="0.37" errorplus="0.37">0.93</radius>
		<magV>15.596</magV>
		<magJ errorminus="0.027" errorplus="0.027">14.227</magJ>
		<magH errorminus="0.026" errorplus="0.026">13.854</magH>
		<magK errorminus="0.043" errorplus="0.043">13.689</magK>
		<temperature errorminus="200.0" errorplus="200.0">5573.0</temperature>
		<metallicity>0.212</metallicity>
		<planet>
			<name>Kepler-255 c</name>
			<radius errorminus="0.105" errorplus="0.105">0.267</radius>
			<period errorminus="3.5e-05" errorplus="3.5e-05">9.946047</period>
			<semimajoraxis>0.092</semimajoraxis>
			<discoverymethod>transit</discoverymethod>
			<transittime errorminus=".002100" errorplus="0.002100" unit="BJD">2455004.700160</transittime>
			<lastupdate>16/11/29</lastupdate>
			<discoveryyear>2014</discoveryyear>
		</planet>
		<planet>
			<name>Kepler-255 b</name>
			<radius errorminus="0.055" errorplus="0.055">0.138</radius>
			<period errorminus="5.2e-05" errorplus="5.2e-05">5.714606</period>
			<semimajoraxis>0.063</semimajoraxis>
			<discoverymethod>transit</discoverymethod>
			<transittime errorminus=".006000" errorplus="0.006000" unit="BJD">2454965.640350</transittime>
			<lastupdate>16/11/29</lastupdate>
			<discoveryyear>2014</discoveryyear>
		</planet>
		<planet>
			<name>Kepler-255 d</name>
			<radius errorminus="0.009" errorplus="0.012">0.118</radius>
			<period errorminus="2.67e-06" errorplus="2.67e-06">1.04562266</period>
			<discoverymethod>transit</discoverymethod>
			<transittime errorminus=".002160" errorplus="0.002160" unit="JD">2454966.918210</transittime>
			<lastupdate>16/11/29</lastupdate>
			<discoveryyear>2016</discoveryyear>
		</planet>
	</star>
</system>
