<system>
	<name>Kepler-816</name>
	<rightascension>19 33 27</rightascension>
	<declination>+39 12 44</declination>
	<distance errorminus="60.23" errorplus="71.99">1059.00</distance>
	<star>
		<name>Kepler-816</name>
		<mass errorminus="0.04" errorplus="0.04">0.9</mass>
		<radius errorminus="0.04" errorplus="0.06">0.85</radius>
		<magV>15.950</magV>
		<magJ errorminus="0.031" errorplus="0.031">14.426</magJ>
		<magH errorminus="0.032" errorplus="0.032">14.045</magH>
		<magK errorminus="0.057" errorplus="0.057">13.892</magK>
		<temperature errorminus="88.41" errorplus="54.61">5286.0</temperature>
		<age errorminus="2.540" errorplus="5.510">4.170</age>
		<metallicity errorminus="0.185" errorplus="0.16">0.16</metallicity>
		<planet>
			<name>Kepler-816 b</name>
			<radius errorminus="0.048" errorplus="0.061">0.914</radius>
			<period errorminus="3.82e-06" errorplus="3.82e-06">10.50682565</period>
			<discoverymethod>transit</discoverymethod>
			<transittime errorminus=".000262" errorplus="0.000262" unit="JD">2455193.082546</transittime>
			<lastupdate>16/11/29</lastupdate>
			<discoveryyear>2016</discoveryyear>
		</planet>
	</star>
</system>
