<system>
	<name>Kepler-865</name>
	<rightascension>19 50 53</rightascension>
	<declination>+43 31 38</declination>
	<distance errorminus="68.31" errorplus="139.31">664.00</distance>
	<star>
		<name>Kepler-865</name>
		<mass errorminus="0.07" errorplus="0.09">0.93</mass>
		<radius errorminus="0.09" errorplus="0.18">0.92</radius>
		<magV>14.480</magV>
		<magJ errorminus="0.023" errorplus="0.023">13.154</magJ>
		<magH errorminus="0.021" errorplus="0.021">12.736</magH>
		<magK errorminus="0.024" errorplus="0.024">12.684</magK>
		<temperature errorminus="208.99" errorplus="287.71">5570.0</temperature>
		<age errorminus="2.560" errorplus="5.150">4.270</age>
		<metallicity errorminus="0.177" errorplus="0.138">-0.01</metallicity>
		<planet>
			<name>Kepler-865 b</name>
			<radius errorminus="0.021" errorplus="0.044">0.222</radius>
			<period errorminus="2.463e-05" errorplus="2.463e-05">14.16399294</period>
			<discoverymethod>transit</discoverymethod>
			<transittime errorminus=".001360" errorplus="0.001360" unit="JD">2454973.590100</transittime>
			<lastupdate>16/11/29</lastupdate>
			<discoveryyear>2016</discoveryyear>
		</planet>
	</star>
</system>
