<system>
	<name>Kepler-265</name>
	<rightascension>19 22 02</rightascension>
	<declination>+41 14 41</declination>
	<star>
		<name>Kepler-265</name>
		<mass>1.03</mass>
		<radius errorminus="0.23" errorplus="0.23">1.1</radius>
		<magV>15.381</magV>
		<magJ errorminus="0.028" errorplus="0.028">14.252</magJ>
		<magH errorminus="0.034" errorplus="0.034">13.935</magH>
		<magK errorminus="0.051" errorplus="0.051">13.897</magK>
		<temperature errorminus="118.0" errorplus="118.0">5835.0</temperature>
		<metallicity>-0.311</metallicity>
		<planet>
			<name>Kepler-265 b</name>
			<radius errorminus="0.04" errorplus="0.04">0.166</radius>
			<period errorminus="6.3e-05" errorplus="6.3e-05">6.846262</period>
			<semimajoraxis>0.069</semimajoraxis>
			<discoverymethod>transit</discoverymethod>
			<transittime errorminus=".005640" errorplus="0.005640" unit="BJD">2454965.170370</transittime>
			<lastupdate>16/11/29</lastupdate>
			<discoveryyear>2014</discoveryyear>
		</planet>
		<planet>
			<name>Kepler-265 c</name>
			<radius errorminus="0.049" errorplus="0.049">0.235</radius>
			<period errorminus="0.000136" errorplus="0.000136">17.028937</period>
			<semimajoraxis>0.127</semimajoraxis>
			<discoverymethod>transit</discoverymethod>
			<transittime errorminus=".004790" errorplus="0.004790" unit="BJD">2454976.336420</transittime>
			<lastupdate>16/11/29</lastupdate>
			<discoveryyear>2014</discoveryyear>
		</planet>
		<planet>
			<name>Kepler-265 d</name>
			<radius errorminus="0.048" errorplus="0.048">0.222</radius>
			<period errorminus="0.000658" errorplus="0.000658">43.130617</period>
			<semimajoraxis>0.236</semimajoraxis>
			<discoverymethod>transit</discoverymethod>
			<transittime errorminus=".009800" errorplus="0.009800" unit="BJD">2454999.275370</transittime>
			<lastupdate>16/11/29</lastupdate>
			<discoveryyear>2014</discoveryyear>
		</planet>
		<planet>
			<name>Kepler-265 e</name>
			<radius errorminus="0.049" errorplus="0.049">0.231</radius>
			<period errorminus="0.001396" errorplus="0.001396">67.831024</period>
			<semimajoraxis>0.319</semimajoraxis>
			<discoverymethod>transit</discoverymethod>
			<transittime errorminus=".013350" errorplus="0.013350" unit="BJD">2454958.896950</transittime>
			<lastupdate>16/11/29</lastupdate>
			<discoveryyear>2014</discoveryyear>
		</planet>
	</star>
</system>
