<system>
	<name>Kepler-805</name>
	<rightascension>19 32 55</rightascension>
	<declination>+45 03 11</declination>
	<distance errorminus="22.61" errorplus="23.97">657.00</distance>
	<star>
		<name>Kepler-805</name>
		<mass errorminus="0.04" errorplus="0.07">1.19</mass>
		<radius errorminus="0.05" errorplus="0.06">1.65</radius>
		<magV>12.547</magV>
		<magJ errorminus="0.018" errorplus="0.018">11.547</magJ>
		<magH errorminus="0.019" errorplus="0.019">11.294</magH>
		<magK errorminus="0.018" errorplus="0.018">11.2</magK>
		<temperature errorminus="66.37" errorplus="55.03">6112.0</temperature>
		<age errorminus="0.690" errorplus="0.600">4.270</age>
		<metallicity errorminus="0.067" errorplus="0.082">-0.06</metallicity>
		<planet>
			<name>Kepler-805 b</name>
			<radius errorminus="0.022" errorplus="0.012">0.258</radius>
			<period errorminus="0.0001259" errorplus="0.0001259">30.8638931</period>
			<discoverymethod>transit</discoverymethod>
			<transittime errorminus=".003300" errorplus="0.003300" unit="JD">2454995.883000</transittime>
			<lastupdate>16/11/29</lastupdate>
			<discoveryyear>2016</discoveryyear>
		</planet>
	</star>
</system>
