<system>
	<name>WASP-65</name>
	<rightascension>08 53 17</rightascension>
	<declination>+08 31 22</declination>
	<distance errorminus="50.00" errorplus="50.00">310.00</distance>
	<star>
		<name>WASP-65</name>
		<mass errorminus="0.16" errorplus="0.12">0.93</mass>
		<radius errorminus="0.05" errorplus="0.05">1.01</radius>
		<magV errorminus="0.040" errorplus="0.040">11.9</magV>
		<magB errorminus="0.010" errorplus="0.010">12.570</magB>
		<magJ errorminus="0.019" errorplus="0.019">10.669</magJ>
		<magH errorminus="0.031" errorplus="0.031">10.440</magH>
		<magK errorminus="0.019" errorplus="0.019">10.346</magK>
		<temperature errorminus="100.0" errorplus="100.0">5600.0</temperature>
		<age>8.000</age>
		<metallicity errorminus="0.07" errorplus="0.07">-0.07</metallicity>
		<spectraltype>G6</spectraltype>
		<planet>
			<name>WASP-65 b</name>
			<mass errorminus="0.16" errorplus="0.16" type="Mass">1.55</mass>
			<radius errorminus="0.059" errorplus="0.059">1.112</radius>
			<period errorminus="1.5e-06" errorplus="1.5e-06">2.3114243</period>
			<semimajoraxis errorminus="0.0017" errorplus="0.0016">0.0334</semimajoraxis>
			<eccentricity>0.000000</eccentricity>
			<inclination errorminus="0.7" errorplus="0.8">88.8</inclination>
			<temperature errorminus="10" errorplus="10">1480</temperature>
			<discoverymethod>transit</discoverymethod>
			<transittime errorminus=".000150" errorplus="0.000150" unit="BJD-TDB">2456110.687720</transittime>
			<lastupdate>16/11/29</lastupdate>
			<discoveryyear>2011</discoveryyear>
		</planet>
	</star>
</system>
